api_brasil/__init__.py
api_brasil/api_client/client_builder.py
api_brasil/features/cep_geolocation/__init__.py
api_brasil/features/cnpj/__init__.py
api_brasil/features/correios/__init__.py
api_brasil/features/cpf/__init__.py
api_brasil/features/interfaces/__init__.py
api_brasil/features/sms/__init__.py
api_brasil/features/vehicles/__init__.py
api_brasil/features/whatsapp/__init__.py
api_brasil-2.0.0.dist-info/LICENSE
api_brasil-2.0.0.dist-info/METADATA
api_brasil-2.0.0.dist-info/WHEEL
api_brasil-2.0.0.dist-info/RECORD
