Metadata-Version: 2.1
Name: api-brasil
Version: 2.0.0
Summary: Este SDK foi desenvolvido para simplificar e agilizar a integração com a plataforma APIBrasil, reduzindo o esforço de desenvolvimento e otimizando o tempo dos usuários.
License: MIT
Author: Ivanildo Barauna de Souza Junior
Author-email: ivanildo.jnr@outlook.com
Requires-Python: >=3.9
Classifier: Development Status :: 4 - Beta
Classifier: Intended Audience :: Developers
Classifier: License :: OSI Approved :: MIT License
Classifier: Programming Language :: Python :: 3
Classifier: Programming Language :: Python :: 3.9
Classifier: Programming Language :: Python :: 3.10
Classifier: Programming Language :: Python :: 3.11
Classifier: Programming Language :: Python :: 3.12
Classifier: Programming Language :: Python :: 3.13
Classifier: Programming Language :: Python :: 3.8
Requires-Dist: requests (>=2.32.3,<3.0.0)
Project-URL: API-Docs, https://apibrasil.com.br/documentacoes
Project-URL: BugTracker, https://github.com/ivanildobarauna-dev/apibrasil-py/issues
Project-URL: Homepage, https://apibrasi.com.br
Project-URL: Repository, https://github.com/ivanildobarauna-dev/apibrasil-py
